deriva/__init__.py
deriva/workbench/__init__.py
deriva/workbench/__main__.py
deriva/workbench/app.py
deriva/workbench/browser.py
deriva/workbench/editor.py
deriva/workbench/options.py
deriva/workbench/resources.py
deriva/workbench/window.py
deriva/workbench/editors/__init__.py
deriva/workbench/editors/asset.py
deriva/workbench/editors/citation.py
deriva/workbench/editors/column_display.py
deriva/workbench/editors/common.py
deriva/workbench/editors/display.py
deriva/workbench/editors/foreign_key.py
deriva/workbench/editors/json_editor.py
deriva/workbench/editors/key_display.py
deriva/workbench/editors/markdown_patterns.py
deriva/workbench/editors/pseudo_column.py
deriva/workbench/editors/sortkeys.py
deriva/workbench/editors/source_definitions.py
deriva/workbench/editors/tabbed_contexts.py
deriva/workbench/editors/table.py
deriva/workbench/editors/table_display.py
deriva/workbench/editors/visible_sources.py
deriva/workbench/icons/workbench.icns
deriva/workbench/icons/workbench.ico
deriva/workbench/icons/workbench.png
deriva/workbench/tasks/__init__.py
deriva/workbench/tasks/base.py
deriva/workbench/tasks/dump.py
deriva_workbench-0.1.2.dist-info/LICENSE
deriva_workbench-0.1.2.dist-info/METADATA
deriva_workbench-0.1.2.dist-info/WHEEL
deriva_workbench-0.1.2.dist-info/entry_points.txt
deriva_workbench-0.1.2.dist-info/top_level.txt
deriva_workbench-0.1.2.dist-info/RECORD
