Metadata-Version: 2.1
Name: deriva-workbench
Version: 0.1.2
Summary: Schema Workbench for the DERIVA platform.
Home-page: https://github.com/informatics-isi-edu
Author: USC Information Sciences Institute, Informatics Systems Research Division
Author-email: isrd-support@isi.edu
Maintainer: USC Information Sciences Institute, Informatics Systems Research Division
Maintainer-email: isrd-support@isi.edu
License: GNU GPL 3.0
Classifier: Intended Audience :: Science/Research
Classifier: Intended Audience :: Developers
Classifier: License :: OSI Approved :: GNU General Public License v3 (GPLv3)
Classifier: Operating System :: POSIX
Classifier: Operating System :: MacOS :: MacOS X
Classifier: Operating System :: Microsoft :: Windows
Classifier: Programming Language :: Python
Classifier: Programming Language :: Python :: 3.8
Classifier: Programming Language :: Python :: 3.9
Classifier: Programming Language :: Python :: 3.10
Classifier: Programming Language :: Python :: 3.11
Classifier: Programming Language :: Python :: 3.12
License-File: LICENSE
Requires-Dist: deriva >=1.5.0
Requires-Dist: deriva-qt >=1.5.0
Provides-Extra: pyqt5
Requires-Dist: PyQt5 ==5.11.3 ; extra == 'pyqt5'
Provides-Extra: pyqt5-stubs
Requires-Dist: PyQt5-stubs <5.12 ; extra == 'pyqt5-stubs'
Provides-Extra: pyqtwebengine
Requires-Dist: PyQtWebEngine >=5.15.4 ; extra == 'pyqtwebengine'
Provides-Extra: pyqtwebengine-stubs
Requires-Dist: PyQt5-stubs >=5.15 ; extra == 'pyqtwebengine-stubs'
